equium/__init__.py
equium-0.0.1.dist-info/LICENSE
equium-0.0.1.dist-info/WHEEL
equium-0.0.1.dist-info/METADATA
equium-0.0.1.dist-info/RECORD
