Metadata-Version: 2.1
Name: equium
Version: 0.0.1
Summary: Experimenting with Equality
License: BSD-3-Clause
Author: John Paulett
Author-email: john@paulett.org
Requires-Python: >=3.7,<4.0
Classifier: License :: OSI Approved :: BSD License
Classifier: Programming Language :: Python :: 3
Classifier: Programming Language :: Python :: 3.7
Classifier: Programming Language :: Python :: 3.8
